{
  "trackers": [
    {
      "type": "unknown",
      "url": "http://matchid.io/"
    },
    {
      "type": "unknown",
      "url": "https://matchid.io/"
    },
    {
      "type": "unknown",
      "url": "https://matchid.io/assets/dsfr/dsfr.min.css"
    },
    {
      "type": "unknown",
      "url": "https://matchid.io/assets/css/global.css"
    },
    {
      "type": "unknown",
      "url": "https://matchid.io/assets/dsfr/artwork/light.svg"
    },
    {
      "type": "unknown",
      "url": "https://matchid.io/assets/dsfr/artwork/dark.svg"
    },
    {
      "type": "unknown",
      "url": "https://matchid.io/assets/dsfr/artwork/system.svg"
    },
    {
      "type": "unknown",
      "url": "https://matchid.io/assets/images/favicon.svg"
    },
    {
      "type": "unknown",
      "url": "https://matchid.io/assets/images/frontend-validation-stats.svg"
    },
    {
      "type": "unknown",
      "url": "https://static.cloudflareinsights.com/beacon.min.js/vb26e4fa9e5134444860be286fd8771851679335129114"
    },
    {
      "type": "unknown",
      "url": "https://matchid.io/assets/images/genealogy.svg"
    },
    {
      "type": "unknown",
      "url": "https://matchid.io/assets/images/doctor-man-2.svg"
    },
    {
      "type": "unknown",
      "url": "https://matchid.io/assets/images/datascientist.svg"
    },
    {
      "type": "unknown",
      "url": "https://matchid.io/assets/images/fabien.jpeg"
    },
    {
      "type": "unknown",
      "url": "https://matchid.io/assets/images/cristian.jpeg"
    },
    {
      "type": "unknown",
      "url": "https://matchid.io/assets/images/martin.jpeg"
    },
    {
      "type": "unknown",
      "url": "https://matchid.io/cdn-cgi/scripts/7d0fa10a/cloudflare-static/rocket-loader.min.js"
    },
    {
      "type": "unknown",
      "url": "https://www.dailymotion.com/embed/video/x7okqx1"
    },
    {
      "type": "unknown",
      "url": "https://deces.matchid.io/search?q=Pompidou%20Georges"
    },
    {
      "type": "unknown",
      "url": "https://matchid.io/assets/images/datascience.jpg"
    },
    {
      "type": "unknown",
      "url": "https://code.iconify.design/2/2.1.0/iconify.min.js"
    },
    {
      "type": "unknown",
      "url": "https://pagead2.googlesyndication.com/pagead/js/adsbygoogle.js?client=ca-pub-6277851622494904"
    },
    {
      "type": "unknown",
      "url": "https://matchid.io/assets/dsfr/dsfr.module.js"
    },
    {
      "type": "google tag manager",
      "url": "https://www.googletagmanager.com/gtag/js?id=G-49J1J0GERX",
      "details": {
        "id": "google tag manager",
        "message": "Use hosted Matomo instance"
      }
    },
    {
      "type": "unknown",
      "url": "https://static1.dmcdn.net/playerv5/dmp.infopack.0d33ffc6e419b9303ab0.js"
    },
    {
      "type": "unknown",
      "url": "https://static1.dmcdn.net/playerv5/dmp.jq_flight.3033f0d7176196134921.js"
    },
    {
      "type": "unknown",
      "url": "https://static1.dmcdn.net/playerv5/dmp.photon_manifest.9a633a46dc2e2d3be8fd.js"
    },
    {
      "type": "unknown",
      "url": "https://static1.dmcdn.net/playerv5/dmp.photon_vendor.d2635c3d1308270d60f4.js"
    },
    {
      "type": "unknown",
      "url": "https://static1.dmcdn.net/playerv5/dmp.photon_boot.c25ae0e9683786245dda.js"
    },
    {
      "type": "unknown",
      "url": "https://static1.dmcdn.net/playerv5/dmp.photon_app.2fb4b0927db191fef708.js"
    },
    {
      "type": "unknown",
      "url": "https://static1.dmcdn.net/playerv5/dmp.photon_player.95bde0ce66568dbcf7fb.js"
    },
    {
      "type": "unknown",
      "url": "https://static1.dmcdn.net/playerv5/dmp.locale-en-US.331ac040134065321ad6.json"
    },
    {
      "type": "unknown",
      "url": "https://pebed.dm-event.net/"
    },
    {
      "type": "unknown",
      "url": "https://static.cloudflareinsights.com/beacon.min.js/vb26e4fa9e5134444860be286fd8771851679335129114"
    },
    {
      "type": "unknown",
      "url": "https://deces.matchid.io/css/global.css"
    },
    {
      "type": "unknown",
      "url": "https://deces.matchid.io/css/matchid.min.css"
    },
    {
      "type": "unknown",
      "url": "https://deces.matchid.io/build/module/bundle.css"
    },
    {
      "type": "unknown",
      "url": "https://deces.matchid.io/cdn-cgi/scripts/7d0fa10a/cloudflare-static/rocket-loader.min.js"
    },
    {
      "type": "unknown",
      "url": "https://deces.matchid.io/js/matchid.min.js"
    },
    {
      "type": "unknown",
      "url": "https://vendorlist.dmcdn.net/v2/vendor-list.json"
    },
    {
      "type": "unknown",
      "url": "https://www.dailymotion.com/player/metadata/video/x7okqx1?embedder=https%3A%2F%2Fmatchid.io%2F&locale=en-US&dmV1st=467480ea-130c-4b6c-a6c1-8b4f2ac6aca3&dmTs=776506&is_native_app=0"
    },
    {
      "type": "google",
      "url": "https://imasdk.googleapis.com/js/sdkloader/ima3.js",
      "details": {
        "id": "google",
        "message": "Use hosted Matomo instance"
      }
    },
    {
      "type": "unknown",
      "url": "https://deces.matchid.io/build/nomodule/main.js"
    },
    {
      "type": "unknown",
      "url": "https://pagead2.googlesyndication.com/pagead/managed/js/adsense/m202303210101/show_ads_impl.js"
    },
    {
      "type": "google analytics",
      "url": "https://googleads.g.doubleclick.net/pagead/html/r20230322/r20190131/zrt_lookup.html",
      "details": {
        "id": "google analytics",
        "message": "Use hosted Matomo instance"
      }
    },
    {
      "type": "unknown",
      "url": "https://matchid.io/assets/dsfr/dsfr.module.js"
    },
    {
      "type": "unknown",
      "url": "https://deces.matchid.io/cdn-cgi/rum?"
    },
    {
      "type": "google",
      "url": "https://analytics.google.com/g/collect?v=2&tid=G-49J1J0GERX&gtm=45je33m0&_p=854362280&_gaz=1&cid=590568499.1679792951&ul=en-us&sr=800x600&uaa=&uab=&uafvl=&uamb=0&uam=&uap=&uapv=&uaw=0&_s=1&sid=1679792950&sct=1&seg=0&dl=https%3A%2F%2Fmatchid.io%2F&dt=matchID&en=page_view&_fv=1&_nsi=1&_ss=1&_ee=1",
      "details": {
        "id": "google",
        "message": "Use hosted Matomo instance"
      }
    },
    {
      "type": "google analytics",
      "url": "https://stats.g.doubleclick.net/g/collect?v=2&tid=G-49J1J0GERX&cid=590568499.1679792951&gtm=45je33m0&aip=1",
      "details": {
        "id": "google analytics",
        "message": "Use hosted Matomo instance"
      }
    },
    {
      "type": "unknown",
      "url": "https://static1.dmcdn.net/playerv5/dmp.omweb.cdfef7829ffd9944e2f5.js"
    },
    {
      "type": "unknown",
      "url": "https://static1.dmcdn.net/playerv5/dmp.omid_session_client.63164f6b3825d0575556.js"
    },
    {
      "type": "google",
      "url": "https://www.gstatic.com/cv/js/sender/v1/cast_sender.js",
      "details": {
        "id": "google",
        "message": "Use hosted Matomo instance"
      }
    },
    {
      "type": "unknown",
      "url": "https://static1.dmcdn.net/playerv5/fonts/Retina-Regular.039feafb8e07151a9fa79dd01263f273.woff2"
    },
    {
      "type": "unknown",
      "url": "https://speedtest.dailymotion.com/latencies.js"
    },
    {
      "type": "google",
      "url": "https://imasdk.googleapis.com/js/core/bridge3.565.0_en.html",
      "details": {
        "id": "google",
        "message": "Use hosted Matomo instance"
      }
    },
    {
      "type": "unknown",
      "url": "https://s0.2mdn.net/instream/video/client.js"
    },
    {
      "type": "unknown",
      "url": "https://static1.dmcdn.net/playerv5/fonts/Retina-Regular.039feafb8e07151a9fa79dd01263f273.woff2"
    },
    {
      "type": "unknown",
      "url": "https://pagead2.googlesyndication.com/omsdk/releases/live/omweb-v1.js"
    },
    {
      "type": "unknown",
      "url": "https://pebed.dm-event.net/"
    },
    {
      "type": "unknown",
      "url": "https://api.iconify.design/ri.json?icons=github-line"
    },
    {
      "type": "unknown",
      "url": "https://partner.googleadservices.com/gampad/cookie.js?domain=matchid.io&callback=_gfp_s_&client=ca-pub-6277851622494904"
    },
    {
      "type": "google",
      "url": "https://adservice.google.com/adsid/integrator.js?domain=matchid.io",
      "details": {
        "id": "google",
        "message": "Use hosted Matomo instance"
      }
    },
    {
      "type": "google analytics",
      "url": "https://googleads.g.doubleclick.net/pagead/ads?client=ca-pub-6277851622494904&output=html&adk=1812271804&adf=3025194257&lmt=1672709617&plat=1%3A8%2C2%3A8%2C3%3A2162688%2C4%3A2162688%2C9%3A32776%2C16%3A8388608%2C17%3A32%2C24%3A32%2C25%3A32%2C30%3A1048576%2C32%3A32%2C41%3A32%2C42%3A32&format=0x0&url=https%3A%2F%2Fmatchid.io%2F&ea=0&pra=5&wgl=1&uach=WyIiLCIiLCIiLCIiLCIiLFtdLGZhbHNlLG51bGwsIiIsW10sZmFsc2Vd&dt=1679792950612&bpp=20&bdt=939&idt=352&shv=r20230322&mjsv=m202303210101&ptt=9&saldr=aa&abxe=1&nras=1&correlator=4311895266723&frm=20&pv=2&ga_vid=590568499.1679792951&ga_sid=1679792951&ga_hid=854362280&ga_fc=1&u_tz=0&u_his=2&u_h=600&u_w=800&u_ah=600&u_aw=800&u_cd=24&u_sd=1&dmc=8&adx=-12245933&ady=-12245933&biw=800&bih=600&scr_x=0&scr_y=0&eid=44777877%2C42532090%2C44759842%2C44759876%2C44759927%2C44786632%2C21065724&oid=2&pvsid=4168090713593492&tmod=1166709529&uas=0&nvt=1&fc=1920&brdim=0%2C0%2C0%2C0%2C800%2C0%2C800%2C600%2C800%2C600&vis=1&rsz=%7C%7Cs%7C&abl=NS&fu=32768&bc=31&ifi=1&uci=a!1&fsb=1&dtd=384",
      "details": {
        "id": "google analytics",
        "message": "Use hosted Matomo instance"
      }
    },
    {
      "type": "unknown",
      "url": "https://static1.dmcdn.net/playerv5/fonts/RetinaMedium.2811330fd8cd981352918b4059564b10.woff2"
    },
    {
      "type": "unknown",
      "url": "https://static1.dmcdn.net/playerv5/fonts/RetinaMedium.2811330fd8cd981352918b4059564b10.woff2"
    },
    {
      "type": "unknown",
      "url": "https://pagead2.googlesyndication.com/getconfig/sodar?sv=200&tid=gda&tv=r20230322&st=env"
    },
    {
      "type": "unknown",
      "url": "https://deces.matchid.io/deces/api/v1/version"
    },
    {
      "type": "unknown",
      "url": "https://deces.matchid.io/favicon.svg"
    },
    {
      "type": "unknown",
      "url": "https://matchid.io/assets/dsfr/artwork/light.svg"
    },
    {
      "type": "unknown",
      "url": "https://matchid.io/assets/dsfr/artwork/dark.svg"
    },
    {
      "type": "unknown",
      "url": "https://matchid.io/assets/dsfr/artwork/system.svg"
    },
    {
      "type": "unknown",
      "url": "https://matchid.io/cdn-cgi/rum?"
    },
    {
      "type": "unknown",
      "url": "https://tpc.googlesyndication.com/sodar/sodar2.js"
    },
    {
      "type": "unknown",
      "url": "https://deces.matchid.io/deces/api/v1/search"
    },
    {
      "type": "unknown",
      "url": "https://tpc.googlesyndication.com/sodar/sodar2/225/runner.html"
    },
    {
      "type": "google",
      "url": "https://www.google.com/recaptcha/api2/aframe",
      "details": {
        "id": "google",
        "message": "Use hosted Matomo instance"
      }
    },
    {
      "type": "unknown",
      "url": "https://pagead2.googlesyndication.com/bg/t4_aWeuLa_BO9IGQ3R3HcB0TaFNoER_W7PQrl5RFgV0.js"
    },
    {
      "type": "unknown",
      "url": "https://pagead2.googlesyndication.com/pagead/sodar?id=sodar2&v=225&li=gda_r20230322&jk=4168090713593492&rc="
    },
    {
      "type": "unknown",
      "url": "https://tpc.googlesyndication.com/generate_204?KxIV0g"
    },
    {
      "type": "unknown",
      "url": "https://deces.matchid.io/liveConfig.json"
    },
    {
      "type": "google tag manager",
      "url": "https://www.googletagmanager.com/gtag/js?id=G-49J1J0GERX",
      "details": {
        "id": "google tag manager",
        "message": "Use hosted Matomo instance"
      }
    },
    {
      "type": "unknown",
      "url": "https://pagead2.googlesyndication.com/pagead/js/adsbygoogle.js?client=ca-pub-6277851622494904"
    },
    {
      "type": "unknown",
      "url": "https://pagead2.googlesyndication.com/pagead/managed/js/adsense/m202303210101/show_ads_impl.js"
    },
    {
      "type": "unknown",
      "url": "https://deces.matchid.io/male.svg"
    },
    {
      "type": "unknown",
      "url": "https://upload.wikimedia.org/wikipedia/commons/thumb/2/2a/Georges_Pompidou_1969_(cropped).jpg/80px-Georges_Pompidou_1969_(cropped).jpg"
    },
    {
      "type": "unknown",
      "url": "https://partner.googleadservices.com/gampad/cookie.js?domain=deces.matchid.io&callback=_gfp_s_&client=ca-pub-6277851622494904&cookie=ID%3D3d67e4ec2427ccd8-222e51b7d2db0052%3AT%3D1679792951%3ART%3D1679792951%3AS%3DALNI_MZLaV_lb8IROkkXAN4YQdExMsFysA&gpic=UID%3D000009663202a22f%3AT%3D1679792951%3ART%3D1679792951%3AS%3DALNI_MaDA8mCIf556zZ0kaH57RgmjTWg8Q"
    },
    {
      "type": "google",
      "url": "https://adservice.google.com/adsid/integrator.js?domain=deces.matchid.io",
      "details": {
        "id": "google",
        "message": "Use hosted Matomo instance"
      }
    },
    {
      "type": "google analytics",
      "url": "https://googleads.g.doubleclick.net/pagead/ads?client=ca-pub-6277851622494904&output=html&adk=1812271804&adf=3279755396&plat=1%3A512%2C2%3A512%2C3%3A2163200%2C4%3A2163200%2C8%3A512%2C9%3A512%2C16%3A8388608%2C17%3A32%2C24%3A32%2C25%3A32%2C26%3A512%2C27%3A512%2C30%3A1049088%2C32%3A32%2C41%3A32%2C42%3A32&format=0x0&url=https%3A%2F%2Fmatchid.io%2F&ea=0&pra=5&wgl=1&uach=WyIiLCIiLCIiLCIiLCIiLFtdLGZhbHNlLG51bGwsIiIsW10sZmFsc2Vd&dt=1679792951989&bpp=20&bdt=1903&idt=97&shv=r20230322&mjsv=m202303210101&ptt=9&saldr=aa&cookie=ID%3D3d67e4ec2427ccd8-222e51b7d2db0052%3AT%3D1679792951%3ART%3D1679792951%3AS%3DALNI_MZLaV_lb8IROkkXAN4YQdExMsFysA&gpic=UID%3D000009663202a22f%3AT%3D1679792951%3ART%3D1679792951%3AS%3DALNI_MaDA8mCIf556zZ0kaH57RgmjTWg8Q&nras=1&correlator=7383677247416&frm=24&ife=1&pv=2&ga_vid=590568499.1679792951&ga_sid=1679792952&ga_hid=1422110120&ga_fc=1&nhd=1&u_tz=0&u_his=2&u_h=600&u_w=800&u_ah=600&u_aw=800&u_cd=24&u_sd=1&dmc=8&adx=-12245933&ady=-12245933&biw=-12245933&bih=-12245933&isw=384&ish=520&ifk=775856145&scr_x=-12245933&scr_y=-12245933&eid=44777877%2C42532090%2C44759842%2C44759876%2C44759927%2C31073107%2C31073262%2C44767166%2C44786919%2C44787455&oid=2&pvsid=764662003567941&tmod=1166709529&uas=0&nvt=1&fsapi=1&brdim=0%2C0%2C0%2C0%2C800%2C0%2C800%2C600%2C384%2C520&vis=1&rsz=%7C%7Cs%7C&abl=NS&fu=0&bc=31&ifi=1&uci=1.f2u1blmt10wk&fsb=1&dtd=125",
      "details": {
        "id": "google analytics",
        "message": "Use hosted Matomo instance"
      }
    },
    {
      "type": "unknown",
      "url": "https://pagead2.googlesyndication.com/getconfig/sodar?sv=200&tid=gda&tv=r20230322&st=env"
    },
    {
      "type": "unknown",
      "url": "https://tpc.googlesyndication.com/sodar/sodar2.js"
    },
    {
      "type": "unknown",
      "url": "https://tpc.googlesyndication.com/sodar/sodar2/225/runner.html"
    },
    {
      "type": "google",
      "url": "https://www.google.com/recaptcha/api2/aframe",
      "details": {
        "id": "google",
        "message": "Use hosted Matomo instance"
      }
    },
    {
      "type": "unknown",
      "url": "https://pagead2.googlesyndication.com/pagead/sodar?id=sodar2&v=225&t=2&li=gda_r20230322&jk=4168090713593492&bg=!Li2lLXnNAAbO2UOH7tk7ADkAdvg8WjahfBpfPTJ-UnXqIaQAMz8gQwVladycPo5_ml493CcsdHbMiEwWhLTUmGroqZglC9RS18UCAAAAdlIAAAADaAEHmQMBCs6wN1vtE23dnMJDrFpHsrESz0c-kjgPEYuJ0pe0BUUcGj1bLUUvO0Gk6UbJwsq-l51vBSnJamTUA__gssWGvds9wOz7lrerCFJnNO29s6ukFfooKNhbmd4NcSF-ETMiOwEqw-aIeBEisj0_JYU6fac1RBjLMP9H6je6Mb2sU-lb17WKcHqBueGctAWNhWaKVXPvbGy_0nrhotJg6_Z76wkNY8lQgqrU6MCl9h9I7Iem9CFIagVuOLhh2j6g1imVYw_4euJb1OsUo9srvBh1F9lVmkLGNS_p_1tggRJhUnhjtGD9EcFMbFJbTQndcM2h-PfT2nOt2WUHAXEUpJvmEXYUx_X3QpUgf5J2u0kJL41_Yv0aj48JT8-uceu3OSdlw9blgwpPkwUqA0-p5BEKwfpfQMg9mB3r3bwGMh0jxdd2673S5DWGO0TsIci_HdGnvvEbKiYNxPNUrCUTLP2Zk_osLlRazCwFAQgxKtlIboVYRs4o-861ADOspTYgGnSYAmVlOM9xtuyI6XCAqRFpO7ERvdEfKte89hRHe8SLhyVXprkQ13AM3nEenQiKC22e_UdJ9Y9OG7doj4jsyRJKNZz5cCZ5MBQlF5xOyzQ6o1vI2375Ci3rJuws-MKJtLYfTvnoSoPRAq4RvCHGxZncJZOafdeSNTIs8e_BCglyaqquHg9q8eC4wUFE7othTa9KTUGNRjhcSeD-qzBtfg8t0V3HeHabXATDLWsw_Vtz2HKEkg8fxF_BdnZ6lDGfQLBkg6f9J-Il5kn6CBih_E7vtOUXyW7RTshOONackvqXV3gNrB_du6TRWboYuTEeGlkMf_NKw4aJ-3G2NjpmS3Im_qOQRerPN8j96jr69kThDsXmWGt1TJJWNUuhBLHHtY1xijPBbqMrGDsv7JLHJInuR_fHmIWwVO4M-R33Od2FILdTWAmlEufcHNCQuMTmTT7Yvjl0H2F1BbZbGA-rBI4f7wa3ZF_-NjUsGb18nnC-NAGiHTUlv50p2giiCWOpMTj7_w"
    },
    {
      "type": "unknown",
      "url": "https://pagead2.googlesyndication.com/pagead/sodar?id=sodar2&v=225&li=gda_r20230322&jk=764662003567941&rc="
    },
    {
      "type": "unknown",
      "url": "https://tpc.googlesyndication.com/generate_204?fph89w"
    },
    {
      "type": "unknown",
      "url": "https://pagead2.googlesyndication.com/pagead/sodar?id=sodar2&v=225&t=2&li=gda_r20230322&jk=764662003567941&bg=!BgWlBVHNAAbO2UOH7tk7ADkAdvg8Wiq_HzQV6XtVZ6zagw3H9tSeCwXv-gWcz2iLjfrkEc6UHo215iBFwseSay2ysjucmr0U02sCAAAAj1IAAAADaAEHmQMEJ2EDcaQe52lIAi5e8f82uzrKwRF5DwUq0-U3LDd-1FjWCinh9Hhwh_yzqN-2D2S6ds6gBr7QYT1iHQJPr4Vn26yZDzo7qXCrP9M44aY5y2C1VKISqeZcDMABK9IUIdpo4dNQVulKE_UxtvepUw--_7pPRvnz_GR5ksWqTf5rhUttifr45-Nr8FtFvXTzVXWAIqwviQ8kV0FuHrvCkQrFwmwIN5IFDP0ww3MrXDklXYkIlN8-M3Dtsrm829yfEfdOPwektpTD_DDsBPMZwL_UFzWv0w83VrHvpgsXptGMSZVQHbEMTPqjoFCbR5Q_NRfC2zmIY6EO5MX-nuZRr_AsZJW7qcvEqJECzY-YLsABpkQsr6Vguo5YpZ3NmGXl3yf7ZYYRVnNKc6Ebg4lAdp2NiBP9omnrxEp0LQlKUBHmPhd-SFtYYfl3-mw432hvuPa1gdn-AW0AZytJwwpfd6KNN-0xCqbhfpSFfMtR_qyuBk7sxXBMj95bMs686Tc62nyJ6k4WtMLl1A1aSPE0M5NHmdJGSaKQhh2VqzLq1UOYBg7aOBEQbzd2dXiyzWD61EE6Sm7whBXmDuvN4dMOkGJDZvMJrV-FoLoIPzCcuD7pcpCLSIhLM3iS8c6Ci5svdobgUlJ_I5Brnq7CGavJVwO9TUm9RlZN5sz6vJYt0W3G4a_0hq4XkOWVqGxhZXAAfc1yzv1-PnvbqQYwy7PVDMm4KTCwCHuF_6ebbDAKZHApGeJ3rSmRtA2ZbOSXhj9AW-41C6kqte9pUp2zzIsi_Im67LGEksXNKnOlnQCGVcJ-myjvQPPLpi8cw-FQCS0LVHln2of92ErEubO-s8sKUjPfI9nnpqNHoT14i02mCi2wL4vmDBRrgTLqRH-6Ec44Eo39bjOZwrNL7r21SfOfSFWnJ_wln2eGRFYLNqQ9MZ5SSH8rayuAtBKt-TjnGnwatgQL8RjzrRVhomZvMHGctaMIyWgneGRhYLXctXeWQxuTKWuOq-HiGIe9KDSuh9cCfIAHE4Av-g"
    }
  ],
  "cookies": [],
  "headers": {
    "access-control-allow-origin": "*",
    "age": "157",
    "alt-svc": "h3=\":443\"; ma=86400, h3-29=\":443\"; ma=86400",
    "cache-control": "max-age=600",
    "cf-cache-status": "DYNAMIC",
    "cf-ray": "7adb81af5a736428-SJC",
    "content-encoding": "br",
    "content-type": "text/html; charset=utf-8",
    "date": "Sun, 26 Mar 2023 01:09:09 GMT",
    "expires": "Sun, 26 Mar 2023 01:15:41 GMT",
    "last-modified": "Tue, 03 Jan 2023 01:33:37 GMT",
    "nel": "{\"success_fraction\":0,\"report_to\":\"cf-nel\",\"max_age\":604800}",
    "report-to": "{\"endpoints\":[{\"url\":\"https:\\/\\/a.nel.cloudflare.com\\/report\\/v3?s=Z0m1wNzFt8c%2BbX1LYqJ5YCSXEZPoNesSCxMhatHpsbCVPnc3IcI1lqkoCmTDRCiyj3F9bVGxmER9rIgGSry1FXG9LW%2F%2FoJd%2BMk4NcDY80Alae%2FZoZDpAdPCa0p5D\"}],\"group\":\"cf-nel\",\"max_age\":604800}",
    "server": "cloudflare",
    "strict-transport-security": "max-age=15552000; includeSubDomains; preload",
    "vary": "Accept-Encoding",
    "via": "1.1 varnish",
    "x-cache": "HIT",
    "x-cache-hits": "2",
    "x-content-type-options": "nosniff",
    "x-fastly-request-id": "ccce9a0355e56420cc67c21e7897fe7eb383987f",
    "x-github-request-id": "0E10:7611:DB4077:FB021A:641F9A65",
    "x-proxy-cache": "MISS",
    "x-served-by": "cache-sjc10061-SJC",
    "x-timer": "S1679792950.661484,VS0,VE1"
  },
  "endpoints": [
    {
      "hostname": "www.matchid.io",
      "ip": "172.67.179.218",
      "geoip": {
        "continent": {
          "code": "NA",
          "geoname_id": 6255149,
          "names": {
            "de": "Nordamerika",
            "en": "North America",
            "es": "Norteamérica",
            "fr": "Amérique du Nord",
            "ja": "北アメリカ",
            "pt-BR": "América do Norte",
            "ru": "Северная Америка",
            "zh-CN": "北美洲"
          }
        },
        "country": {
          "geoname_id": 6252001,
          "iso_code": "US",
          "names": {
            "de": "Vereinigte Staaten",
            "en": "United States",
            "es": "Estados Unidos",
            "fr": "États Unis",
            "ja": "アメリカ",
            "pt-BR": "EUA",
            "ru": "США",
            "zh-CN": "美国"
          }
        },
        "location": {
          "accuracy_radius": 1000,
          "latitude": 37.751,
          "longitude": -97.822,
          "time_zone": "America/Chicago"
        },
        "registered_country": {
          "geoname_id": 6252001,
          "iso_code": "US",
          "names": {
            "de": "Vereinigte Staaten",
            "en": "United States",
            "es": "Estados Unidos",
            "fr": "États Unis",
            "ja": "アメリカ",
            "pt-BR": "EUA",
            "ru": "США",
            "zh-CN": "美国"
          }
        }
      }
    },
    {
      "hostname": "matchid.io",
      "ip": "172.67.179.218",
      "geoip": {
        "continent": {
          "code": "NA",
          "geoname_id": 6255149,
          "names": {
            "de": "Nordamerika",
            "en": "North America",
            "es": "Norteamérica",
            "fr": "Amérique du Nord",
            "ja": "北アメリカ",
            "pt-BR": "América do Norte",
            "ru": "Северная Америка",
            "zh-CN": "北美洲"
          }
        },
        "country": {
          "geoname_id": 6252001,
          "iso_code": "US",
          "names": {
            "de": "Vereinigte Staaten",
            "en": "United States",
            "es": "Estados Unidos",
            "fr": "États Unis",
            "ja": "アメリカ",
            "pt-BR": "EUA",
            "ru": "США",
            "zh-CN": "美国"
          }
        },
        "location": {
          "accuracy_radius": 1000,
          "latitude": 37.751,
          "longitude": -97.822,
          "time_zone": "America/Chicago"
        },
        "registered_country": {
          "geoname_id": 6252001,
          "iso_code": "US",
          "names": {
            "de": "Vereinigte Staaten",
            "en": "United States",
            "es": "Estados Unidos",
            "fr": "États Unis",
            "ja": "アメリカ",
            "pt-BR": "EUA",
            "ru": "США",
            "zh-CN": "美国"
          }
        }
      }
    },
    {
      "hostname": "static.cloudflareinsights.com",
      "ip": "104.16.56.101",
      "geoip": {
        "registered_country": {
          "geoname_id": 6252001,
          "iso_code": "US",
          "names": {
            "de": "Vereinigte Staaten",
            "en": "United States",
            "es": "Estados Unidos",
            "fr": "États Unis",
            "ja": "アメリカ",
            "pt-BR": "EUA",
            "ru": "США",
            "zh-CN": "美国"
          }
        }
      }
    },
    {
      "hostname": "www.dailymotion.com",
      "ip": "198.54.200.90",
      "geoip": {
        "continent": {
          "code": "NA",
          "geoname_id": 6255149,
          "names": {
            "de": "Nordamerika",
            "en": "North America",
            "es": "Norteamérica",
            "fr": "Amérique du Nord",
            "ja": "北アメリカ",
            "pt-BR": "América do Norte",
            "ru": "Северная Америка",
            "zh-CN": "北美洲"
          }
        },
        "country": {
          "geoname_id": 6252001,
          "iso_code": "US",
          "names": {
            "de": "Vereinigte Staaten",
            "en": "United States",
            "es": "Estados Unidos",
            "fr": "États Unis",
            "ja": "アメリカ",
            "pt-BR": "EUA",
            "ru": "США",
            "zh-CN": "美国"
          }
        },
        "location": {
          "accuracy_radius": 1000,
          "latitude": 34.0544,
          "longitude": -118.244,
          "time_zone": "America/Los_Angeles"
        },
        "registered_country": {
          "geoname_id": 6252001,
          "iso_code": "US",
          "names": {
            "de": "Vereinigte Staaten",
            "en": "United States",
            "es": "Estados Unidos",
            "fr": "États Unis",
            "ja": "アメリカ",
            "pt-BR": "EUA",
            "ru": "США",
            "zh-CN": "美国"
          }
        },
        "subdivisions": [
          {
            "geoname_id": 5332921,
            "iso_code": "CA",
            "names": {
              "de": "Kalifornien",
              "en": "California",
              "es": "California",
              "fr": "Californie",
              "ja": "カリフォルニア州",
              "pt-BR": "Califórnia",
              "ru": "Калифорния",
              "zh-CN": "加州"
            }
          }
        ]
      }
    },
    {
      "hostname": "deces.matchid.io",
      "ip": "172.67.179.218",
      "geoip": {
        "continent": {
          "code": "NA",
          "geoname_id": 6255149,
          "names": {
            "de": "Nordamerika",
            "en": "North America",
            "es": "Norteamérica",
            "fr": "Amérique du Nord",
            "ja": "北アメリカ",
            "pt-BR": "América do Norte",
            "ru": "Северная Америка",
            "zh-CN": "北美洲"
          }
        },
        "country": {
          "geoname_id": 6252001,
          "iso_code": "US",
          "names": {
            "de": "Vereinigte Staaten",
            "en": "United States",
            "es": "Estados Unidos",
            "fr": "États Unis",
            "ja": "アメリカ",
            "pt-BR": "EUA",
            "ru": "США",
            "zh-CN": "美国"
          }
        },
        "location": {
          "accuracy_radius": 1000,
          "latitude": 37.751,
          "longitude": -97.822,
          "time_zone": "America/Chicago"
        },
        "registered_country": {
          "geoname_id": 6252001,
          "iso_code": "US",
          "names": {
            "de": "Vereinigte Staaten",
            "en": "United States",
            "es": "Estados Unidos",
            "fr": "États Unis",
            "ja": "アメリカ",
            "pt-BR": "EUA",
            "ru": "США",
            "zh-CN": "美国"
          }
        }
      }
    },
    {
      "hostname": "code.iconify.design",
      "ip": "172.67.71.159",
      "geoip": {
        "continent": {
          "code": "NA",
          "geoname_id": 6255149,
          "names": {
            "de": "Nordamerika",
            "en": "North America",
            "es": "Norteamérica",
            "fr": "Amérique du Nord",
            "ja": "北アメリカ",
            "pt-BR": "América do Norte",
            "ru": "Северная Америка",
            "zh-CN": "北美洲"
          }
        },
        "country": {
          "geoname_id": 6252001,
          "iso_code": "US",
          "names": {
            "de": "Vereinigte Staaten",
            "en": "United States",
            "es": "Estados Unidos",
            "fr": "États Unis",
            "ja": "アメリカ",
            "pt-BR": "EUA",
            "ru": "США",
            "zh-CN": "美国"
          }
        },
        "location": {
          "accuracy_radius": 1000,
          "latitude": 37.751,
          "longitude": -97.822,
          "time_zone": "America/Chicago"
        },
        "registered_country": {
          "geoname_id": 6252001,
          "iso_code": "US",
          "names": {
            "de": "Vereinigte Staaten",
            "en": "United States",
            "es": "Estados Unidos",
            "fr": "États Unis",
            "ja": "アメリカ",
            "pt-BR": "EUA",
            "ru": "США",
            "zh-CN": "美国"
          }
        }
      }
    },
    {
      "hostname": "pagead2.googlesyndication.com",
      "ip": "142.250.191.66",
      "geoip": {
        "continent": {
          "code": "NA",
          "geoname_id": 6255149,
          "names": {
            "de": "Nordamerika",
            "en": "North America",
            "es": "Norteamérica",
            "fr": "Amérique du Nord",
            "ja": "北アメリカ",
            "pt-BR": "América do Norte",
            "ru": "Северная Америка",
            "zh-CN": "北美洲"
          }
        },
        "country": {
          "geoname_id": 6252001,
          "iso_code": "US",
          "names": {
            "de": "Vereinigte Staaten",
            "en": "United States",
            "es": "Estados Unidos",
            "fr": "États Unis",
            "ja": "アメリカ",
            "pt-BR": "EUA",
            "ru": "США",
            "zh-CN": "美国"
          }
        },
        "location": {
          "accuracy_radius": 1000,
          "latitude": 37.751,
          "longitude": -97.822,
          "time_zone": "America/Chicago"
        },
        "registered_country": {
          "geoname_id": 6252001,
          "iso_code": "US",
          "names": {
            "de": "Vereinigte Staaten",
            "en": "United States",
            "es": "Estados Unidos",
            "fr": "États Unis",
            "ja": "アメリカ",
            "pt-BR": "EUA",
            "ru": "США",
            "zh-CN": "美国"
          }
        }
      }
    },
    {
      "hostname": "www.googletagmanager.com",
      "ip": "142.251.214.136",
      "geoip": {
        "continent": {
          "code": "NA",
          "geoname_id": 6255149,
          "names": {
            "de": "Nordamerika",
            "en": "North America",
            "es": "Norteamérica",
            "fr": "Amérique du Nord",
            "ja": "北アメリカ",
            "pt-BR": "América do Norte",
            "ru": "Северная Америка",
            "zh-CN": "北美洲"
          }
        },
        "country": {
          "geoname_id": 6252001,
          "iso_code": "US",
          "names": {
            "de": "Vereinigte Staaten",
            "en": "United States",
            "es": "Estados Unidos",
            "fr": "États Unis",
            "ja": "アメリカ",
            "pt-BR": "EUA",
            "ru": "США",
            "zh-CN": "美国"
          }
        },
        "location": {
          "accuracy_radius": 1000,
          "latitude": 37.751,
          "longitude": -97.822,
          "time_zone": "America/Chicago"
        },
        "registered_country": {
          "geoname_id": 6252001,
          "iso_code": "US",
          "names": {
            "de": "Vereinigte Staaten",
            "en": "United States",
            "es": "Estados Unidos",
            "fr": "États Unis",
            "ja": "アメリカ",
            "pt-BR": "EUA",
            "ru": "США",
            "zh-CN": "美国"
          }
        }
      }
    },
    {
      "hostname": "static1.dmcdn.net",
      "ip": "208.111.152.2",
      "geoip": {
        "city": {
          "geoname_id": 5378538,
          "names": {
            "de": "Oakland",
            "en": "Oakland",
            "es": "Oakland",
            "fr": "Oakland",
            "ja": "オークランド",
            "pt-BR": "Oakland",
            "ru": "Окленд",
            "zh-CN": "奥克兰"
          }
        },
        "continent": {
          "code": "NA",
          "geoname_id": 6255149,
          "names": {
            "de": "Nordamerika",
            "en": "North America",
            "es": "Norteamérica",
            "fr": "Amérique du Nord",
            "ja": "北アメリカ",
            "pt-BR": "América do Norte",
            "ru": "Северная Америка",
            "zh-CN": "北美洲"
          }
        },
        "country": {
          "geoname_id": 6252001,
          "iso_code": "US",
          "names": {
            "de": "Vereinigte Staaten",
            "en": "United States",
            "es": "Estados Unidos",
            "fr": "États Unis",
            "ja": "アメリカ",
            "pt-BR": "EUA",
            "ru": "США",
            "zh-CN": "美国"
          }
        },
        "location": {
          "accuracy_radius": 20,
          "latitude": 37.8075,
          "longitude": -122.2644,
          "metro_code": 807,
          "time_zone": "America/Los_Angeles"
        },
        "postal": {
          "code": "94612"
        },
        "registered_country": {
          "geoname_id": 6252001,
          "iso_code": "US",
          "names": {
            "de": "Vereinigte Staaten",
            "en": "United States",
            "es": "Estados Unidos",
            "fr": "États Unis",
            "ja": "アメリカ",
            "pt-BR": "EUA",
            "ru": "США",
            "zh-CN": "美国"
          }
        },
        "subdivisions": [
          {
            "geoname_id": 5332921,
            "iso_code": "CA",
            "names": {
              "de": "Kalifornien",
              "en": "California",
              "es": "California",
              "fr": "Californie",
              "ja": "カリフォルニア州",
              "pt-BR": "Califórnia",
              "ru": "Калифорния",
              "zh-CN": "加州"
            }
          }
        ]
      }
    },
    {
      "hostname": "pebed.dm-event.net",
      "ip": "188.65.124.58",
      "geoip": {
        "city": {
          "geoname_id": 2988507,
          "names": {
            "de": "Paris",
            "en": "Paris",
            "es": "París",
            "fr": "Paris",
            "ja": "パリ",
            "pt-BR": "Paris",
            "ru": "Париж",
            "zh-CN": "巴黎"
          }
        },
        "continent": {
          "code": "EU",
          "geoname_id": 6255148,
          "names": {
            "de": "Europa",
            "en": "Europe",
            "es": "Europa",
            "fr": "Europe",
            "ja": "ヨーロッパ",
            "pt-BR": "Europa",
            "ru": "Европа",
            "zh-CN": "欧洲"
          }
        },
        "country": {
          "geoname_id": 3017382,
          "is_in_european_union": true,
          "iso_code": "FR",
          "names": {
            "de": "Frankreich",
            "en": "France",
            "es": "Francia",
            "fr": "France",
            "ja": "フランス共和国",
            "pt-BR": "França",
            "ru": "Франция",
            "zh-CN": "法国"
          }
        },
        "location": {
          "accuracy_radius": 20,
          "latitude": 48.8323,
          "longitude": 2.4075,
          "time_zone": "Europe/Paris"
        },
        "postal": {
          "code": "75017"
        },
        "registered_country": {
          "geoname_id": 3017382,
          "is_in_european_union": true,
          "iso_code": "FR",
          "names": {
            "de": "Frankreich",
            "en": "France",
            "es": "Francia",
            "fr": "France",
            "ja": "フランス共和国",
            "pt-BR": "França",
            "ru": "Франция",
            "zh-CN": "法国"
          }
        },
        "subdivisions": [
          {
            "geoname_id": 3012874,
            "iso_code": "IDF",
            "names": {
              "de": "Île-de-France",
              "en": "Île-de-France",
              "es": "Isla de Francia",
              "fr": "Île-de-France",
              "pt-BR": "Ilha de França"
            }
          },
          {
            "geoname_id": 2968815,
            "iso_code": "75",
            "names": {
              "de": "Paris",
              "en": "Paris",
              "es": "Paris",
              "fr": "Paris"
            }
          }
        ]
      }
    },
    {
      "hostname": "vendorlist.dmcdn.net",
      "ip": "208.111.152.2",
      "geoip": {
        "city": {
          "geoname_id": 5378538,
          "names": {
            "de": "Oakland",
            "en": "Oakland",
            "es": "Oakland",
            "fr": "Oakland",
            "ja": "オークランド",
            "pt-BR": "Oakland",
            "ru": "Окленд",
            "zh-CN": "奥克兰"
          }
        },
        "continent": {
          "code": "NA",
          "geoname_id": 6255149,
          "names": {
            "de": "Nordamerika",
            "en": "North America",
            "es": "Norteamérica",
            "fr": "Amérique du Nord",
            "ja": "北アメリカ",
            "pt-BR": "América do Norte",
            "ru": "Северная Америка",
            "zh-CN": "北美洲"
          }
        },
        "country": {
          "geoname_id": 6252001,
          "iso_code": "US",
          "names": {
            "de": "Vereinigte Staaten",
            "en": "United States",
            "es": "Estados Unidos",
            "fr": "États Unis",
            "ja": "アメリカ",
            "pt-BR": "EUA",
            "ru": "США",
            "zh-CN": "美国"
          }
        },
        "location": {
          "accuracy_radius": 20,
          "latitude": 37.8075,
          "longitude": -122.2644,
          "metro_code": 807,
          "time_zone": "America/Los_Angeles"
        },
        "postal": {
          "code": "94612"
        },
        "registered_country": {
          "geoname_id": 6252001,
          "iso_code": "US",
          "names": {
            "de": "Vereinigte Staaten",
            "en": "United States",
            "es": "Estados Unidos",
            "fr": "États Unis",
            "ja": "アメリカ",
            "pt-BR": "EUA",
            "ru": "США",
            "zh-CN": "美国"
          }
        },
        "subdivisions": [
          {
            "geoname_id": 5332921,
            "iso_code": "CA",
            "names": {
              "de": "Kalifornien",
              "en": "California",
              "es": "California",
              "fr": "Californie",
              "ja": "カリフォルニア州",
              "pt-BR": "Califórnia",
              "ru": "Калифорния",
              "zh-CN": "加州"
            }
          }
        ]
      }
    },
    {
      "hostname": "imasdk.googleapis.com",
      "ip": "172.217.12.106",
      "geoip": {
        "continent": {
          "code": "NA",
          "geoname_id": 6255149,
          "names": {
            "de": "Nordamerika",
            "en": "North America",
            "es": "Norteamérica",
            "fr": "Amérique du Nord",
            "ja": "北アメリカ",
            "pt-BR": "América do Norte",
            "ru": "Северная Америка",
            "zh-CN": "北美洲"
          }
        },
        "country": {
          "geoname_id": 6252001,
          "iso_code": "US",
          "names": {
            "de": "Vereinigte Staaten",
            "en": "United States",
            "es": "Estados Unidos",
            "fr": "États Unis",
            "ja": "アメリカ",
            "pt-BR": "EUA",
            "ru": "США",
            "zh-CN": "美国"
          }
        },
        "location": {
          "accuracy_radius": 1000,
          "latitude": 37.751,
          "longitude": -97.822,
          "time_zone": "America/Chicago"
        },
        "registered_country": {
          "geoname_id": 6252001,
          "iso_code": "US",
          "names": {
            "de": "Vereinigte Staaten",
            "en": "United States",
            "es": "Estados Unidos",
            "fr": "États Unis",
            "ja": "アメリカ",
            "pt-BR": "EUA",
            "ru": "США",
            "zh-CN": "美国"
          }
        }
      }
    },
    {
      "hostname": "googleads.g.doubleclick.net",
      "ip": "142.251.214.130",
      "geoip": {
        "continent": {
          "code": "NA",
          "geoname_id": 6255149,
          "names": {
            "de": "Nordamerika",
            "en": "North America",
            "es": "Norteamérica",
            "fr": "Amérique du Nord",
            "ja": "北アメリカ",
            "pt-BR": "América do Norte",
            "ru": "Северная Америка",
            "zh-CN": "北美洲"
          }
        },
        "country": {
          "geoname_id": 6252001,
          "iso_code": "US",
          "names": {
            "de": "Vereinigte Staaten",
            "en": "United States",
            "es": "Estados Unidos",
            "fr": "États Unis",
            "ja": "アメリカ",
            "pt-BR": "EUA",
            "ru": "США",
            "zh-CN": "美国"
          }
        },
        "location": {
          "accuracy_radius": 1000,
          "latitude": 37.751,
          "longitude": -97.822,
          "time_zone": "America/Chicago"
        },
        "registered_country": {
          "geoname_id": 6252001,
          "iso_code": "US",
          "names": {
            "de": "Vereinigte Staaten",
            "en": "United States",
            "es": "Estados Unidos",
            "fr": "États Unis",
            "ja": "アメリカ",
            "pt-BR": "EUA",
            "ru": "США",
            "zh-CN": "美国"
          }
        }
      }
    },
    {
      "hostname": "analytics.google.com",
      "ip": "142.251.46.238",
      "geoip": {
        "continent": {
          "code": "NA",
          "geoname_id": 6255149,
          "names": {
            "de": "Nordamerika",
            "en": "North America",
            "es": "Norteamérica",
            "fr": "Amérique du Nord",
            "ja": "北アメリカ",
            "pt-BR": "América do Norte",
            "ru": "Северная Америка",
            "zh-CN": "北美洲"
          }
        },
        "country": {
          "geoname_id": 6252001,
          "iso_code": "US",
          "names": {
            "de": "Vereinigte Staaten",
            "en": "United States",
            "es": "Estados Unidos",
            "fr": "États Unis",
            "ja": "アメリカ",
            "pt-BR": "EUA",
            "ru": "США",
            "zh-CN": "美国"
          }
        },
        "location": {
          "accuracy_radius": 1000,
          "latitude": 43.0382,
          "longitude": -87.91,
          "time_zone": "America/Chicago"
        },
        "registered_country": {
          "geoname_id": 6252001,
          "iso_code": "US",
          "names": {
            "de": "Vereinigte Staaten",
            "en": "United States",
            "es": "Estados Unidos",
            "fr": "États Unis",
            "ja": "アメリカ",
            "pt-BR": "EUA",
            "ru": "США",
            "zh-CN": "美国"
          }
        },
        "subdivisions": [
          {
            "geoname_id": 5279468,
            "iso_code": "WI",
            "names": {
              "en": "Wisconsin",
              "es": "Wisconsin",
              "fr": "Wisconsin",
              "ja": "ウィスコンシン州",
              "ru": "Висконсин",
              "zh-CN": "威斯康辛州"
            }
          }
        ]
      }
    },
    {
      "hostname": "stats.g.doubleclick.net",
      "ip": "142.251.2.156",
      "geoip": {
        "continent": {
          "code": "NA",
          "geoname_id": 6255149,
          "names": {
            "de": "Nordamerika",
            "en": "North America",
            "es": "Norteamérica",
            "fr": "Amérique du Nord",
            "ja": "北アメリカ",
            "pt-BR": "América do Norte",
            "ru": "Северная Америка",
            "zh-CN": "北美洲"
          }
        },
        "country": {
          "geoname_id": 6252001,
          "iso_code": "US",
          "names": {
            "de": "Vereinigte Staaten",
            "en": "United States",
            "es": "Estados Unidos",
            "fr": "États Unis",
            "ja": "アメリカ",
            "pt-BR": "EUA",
            "ru": "США",
            "zh-CN": "美国"
          }
        },
        "location": {
          "accuracy_radius": 1000,
          "latitude": 37.751,
          "longitude": -97.822,
          "time_zone": "America/Chicago"
        },
        "registered_country": {
          "geoname_id": 6252001,
          "iso_code": "US",
          "names": {
            "de": "Vereinigte Staaten",
            "en": "United States",
            "es": "Estados Unidos",
            "fr": "États Unis",
            "ja": "アメリカ",
            "pt-BR": "EUA",
            "ru": "США",
            "zh-CN": "美国"
          }
        }
      }
    },
    {
      "hostname": "www.gstatic.com",
      "ip": "142.250.191.35",
      "geoip": {
        "continent": {
          "code": "NA",
          "geoname_id": 6255149,
          "names": {
            "de": "Nordamerika",
            "en": "North America",
            "es": "Norteamérica",
            "fr": "Amérique du Nord",
            "ja": "北アメリカ",
            "pt-BR": "América do Norte",
            "ru": "Северная Америка",
            "zh-CN": "北美洲"
          }
        },
        "country": {
          "geoname_id": 6252001,
          "iso_code": "US",
          "names": {
            "de": "Vereinigte Staaten",
            "en": "United States",
            "es": "Estados Unidos",
            "fr": "États Unis",
            "ja": "アメリカ",
            "pt-BR": "EUA",
            "ru": "США",
            "zh-CN": "美国"
          }
        },
        "location": {
          "accuracy_radius": 1000,
          "latitude": 37.751,
          "longitude": -97.822,
          "time_zone": "America/Chicago"
        },
        "registered_country": {
          "geoname_id": 6252001,
          "iso_code": "US",
          "names": {
            "de": "Vereinigte Staaten",
            "en": "United States",
            "es": "Estados Unidos",
            "fr": "États Unis",
            "ja": "アメリカ",
            "pt-BR": "EUA",
            "ru": "США",
            "zh-CN": "美国"
          }
        }
      }
    },
    {
      "hostname": "speedtest.dailymotion.com",
      "ip": "198.54.200.91",
      "geoip": {
        "continent": {
          "code": "NA",
          "geoname_id": 6255149,
          "names": {
            "de": "Nordamerika",
            "en": "North America",
            "es": "Norteamérica",
            "fr": "Amérique du Nord",
            "ja": "北アメリカ",
            "pt-BR": "América do Norte",
            "ru": "Северная Америка",
            "zh-CN": "北美洲"
          }
        },
        "country": {
          "geoname_id": 6252001,
          "iso_code": "US",
          "names": {
            "de": "Vereinigte Staaten",
            "en": "United States",
            "es": "Estados Unidos",
            "fr": "États Unis",
            "ja": "アメリカ",
            "pt-BR": "EUA",
            "ru": "США",
            "zh-CN": "美国"
          }
        },
        "location": {
          "accuracy_radius": 1000,
          "latitude": 34.0544,
          "longitude": -118.244,
          "time_zone": "America/Los_Angeles"
        },
        "registered_country": {
          "geoname_id": 6252001,
          "iso_code": "US",
          "names": {
            "de": "Vereinigte Staaten",
            "en": "United States",
            "es": "Estados Unidos",
            "fr": "États Unis",
            "ja": "アメリカ",
            "pt-BR": "EUA",
            "ru": "США",
            "zh-CN": "美国"
          }
        },
        "subdivisions": [
          {
            "geoname_id": 5332921,
            "iso_code": "CA",
            "names": {
              "de": "Kalifornien",
              "en": "California",
              "es": "California",
              "fr": "Californie",
              "ja": "カリフォルニア州",
              "pt-BR": "Califórnia",
              "ru": "Калифорния",
              "zh-CN": "加州"
            }
          }
        ]
      }
    },
    {
      "hostname": "s0.2mdn.net",
      "ip": "142.251.46.230",
      "geoip": {
        "continent": {
          "code": "NA",
          "geoname_id": 6255149,
          "names": {
            "de": "Nordamerika",
            "en": "North America",
            "es": "Norteamérica",
            "fr": "Amérique du Nord",
            "ja": "北アメリカ",
            "pt-BR": "América do Norte",
            "ru": "Северная Америка",
            "zh-CN": "北美洲"
          }
        },
        "country": {
          "geoname_id": 6252001,
          "iso_code": "US",
          "names": {
            "de": "Vereinigte Staaten",
            "en": "United States",
            "es": "Estados Unidos",
            "fr": "États Unis",
            "ja": "アメリカ",
            "pt-BR": "EUA",
            "ru": "США",
            "zh-CN": "美国"
          }
        },
        "location": {
          "accuracy_radius": 1000,
          "latitude": 43.0382,
          "longitude": -87.91,
          "time_zone": "America/Chicago"
        },
        "registered_country": {
          "geoname_id": 6252001,
          "iso_code": "US",
          "names": {
            "de": "Vereinigte Staaten",
            "en": "United States",
            "es": "Estados Unidos",
            "fr": "États Unis",
            "ja": "アメリカ",
            "pt-BR": "EUA",
            "ru": "США",
            "zh-CN": "美国"
          }
        },
        "subdivisions": [
          {
            "geoname_id": 5279468,
            "iso_code": "WI",
            "names": {
              "en": "Wisconsin",
              "es": "Wisconsin",
              "fr": "Wisconsin",
              "ja": "ウィスコンシン州",
              "ru": "Висконсин",
              "zh-CN": "威斯康辛州"
            }
          }
        ]
      }
    },
    {
      "hostname": "api.iconify.design",
      "ip": "104.26.12.204",
      "geoip": {
        "continent": {
          "code": "NA",
          "geoname_id": 6255149,
          "names": {
            "de": "Nordamerika",
            "en": "North America",
            "es": "Norteamérica",
            "fr": "Amérique du Nord",
            "ja": "北アメリカ",
            "pt-BR": "América do Norte",
            "ru": "Северная Америка",
            "zh-CN": "北美洲"
          }
        },
        "country": {
          "geoname_id": 6252001,
          "iso_code": "US",
          "names": {
            "de": "Vereinigte Staaten",
            "en": "United States",
            "es": "Estados Unidos",
            "fr": "États Unis",
            "ja": "アメリカ",
            "pt-BR": "EUA",
            "ru": "США",
            "zh-CN": "美国"
          }
        },
        "location": {
          "accuracy_radius": 1000,
          "latitude": 37.751,
          "longitude": -97.822,
          "time_zone": "America/Chicago"
        },
        "registered_country": {
          "geoname_id": 6252001,
          "iso_code": "US",
          "names": {
            "de": "Vereinigte Staaten",
            "en": "United States",
            "es": "Estados Unidos",
            "fr": "États Unis",
            "ja": "アメリカ",
            "pt-BR": "EUA",
            "ru": "США",
            "zh-CN": "美国"
          }
        }
      }
    },
    {
      "hostname": "partner.googleadservices.com",
      "ip": "142.251.214.130",
      "geoip": {
        "continent": {
          "code": "NA",
          "geoname_id": 6255149,
          "names": {
            "de": "Nordamerika",
            "en": "North America",
            "es": "Norteamérica",
            "fr": "Amérique du Nord",
            "ja": "北アメリカ",
            "pt-BR": "América do Norte",
            "ru": "Северная Америка",
            "zh-CN": "北美洲"
          }
        },
        "country": {
          "geoname_id": 6252001,
          "iso_code": "US",
          "names": {
            "de": "Vereinigte Staaten",
            "en": "United States",
            "es": "Estados Unidos",
            "fr": "États Unis",
            "ja": "アメリカ",
            "pt-BR": "EUA",
            "ru": "США",
            "zh-CN": "美国"
          }
        },
        "location": {
          "accuracy_radius": 1000,
          "latitude": 37.751,
          "longitude": -97.822,
          "time_zone": "America/Chicago"
        },
        "registered_country": {
          "geoname_id": 6252001,
          "iso_code": "US",
          "names": {
            "de": "Vereinigte Staaten",
            "en": "United States",
            "es": "Estados Unidos",
            "fr": "États Unis",
            "ja": "アメリカ",
            "pt-BR": "EUA",
            "ru": "США",
            "zh-CN": "美国"
          }
        }
      }
    },
    {
      "hostname": "adservice.google.com",
      "ip": "142.250.191.66",
      "geoip": {
        "continent": {
          "code": "NA",
          "geoname_id": 6255149,
          "names": {
            "de": "Nordamerika",
            "en": "North America",
            "es": "Norteamérica",
            "fr": "Amérique du Nord",
            "ja": "北アメリカ",
            "pt-BR": "América do Norte",
            "ru": "Северная Америка",
            "zh-CN": "北美洲"
          }
        },
        "country": {
          "geoname_id": 6252001,
          "iso_code": "US",
          "names": {
            "de": "Vereinigte Staaten",
            "en": "United States",
            "es": "Estados Unidos",
            "fr": "États Unis",
            "ja": "アメリカ",
            "pt-BR": "EUA",
            "ru": "США",
            "zh-CN": "美国"
          }
        },
        "location": {
          "accuracy_radius": 1000,
          "latitude": 37.751,
          "longitude": -97.822,
          "time_zone": "America/Chicago"
        },
        "registered_country": {
          "geoname_id": 6252001,
          "iso_code": "US",
          "names": {
            "de": "Vereinigte Staaten",
            "en": "United States",
            "es": "Estados Unidos",
            "fr": "États Unis",
            "ja": "アメリカ",
            "pt-BR": "EUA",
            "ru": "США",
            "zh-CN": "美国"
          }
        }
      }
    },
    {
      "hostname": "tpc.googlesyndication.com",
      "ip": "142.250.189.225",
      "geoip": {
        "continent": {
          "code": "NA",
          "geoname_id": 6255149,
          "names": {
            "de": "Nordamerika",
            "en": "North America",
            "es": "Norteamérica",
            "fr": "Amérique du Nord",
            "ja": "北アメリカ",
            "pt-BR": "América do Norte",
            "ru": "Северная Америка",
            "zh-CN": "北美洲"
          }
        },
        "country": {
          "geoname_id": 6252001,
          "iso_code": "US",
          "names": {
            "de": "Vereinigte Staaten",
            "en": "United States",
            "es": "Estados Unidos",
            "fr": "États Unis",
            "ja": "アメリカ",
            "pt-BR": "EUA",
            "ru": "США",
            "zh-CN": "美国"
          }
        },
        "location": {
          "accuracy_radius": 1000,
          "latitude": 37.751,
          "longitude": -97.822,
          "time_zone": "America/Chicago"
        },
        "registered_country": {
          "geoname_id": 6252001,
          "iso_code": "US",
          "names": {
            "de": "Vereinigte Staaten",
            "en": "United States",
            "es": "Estados Unidos",
            "fr": "États Unis",
            "ja": "アメリカ",
            "pt-BR": "EUA",
            "ru": "США",
            "zh-CN": "美国"
          }
        }
      }
    },
    {
      "hostname": "www.google.com",
      "ip": "142.250.191.68",
      "geoip": {
        "continent": {
          "code": "NA",
          "geoname_id": 6255149,
          "names": {
            "de": "Nordamerika",
            "en": "North America",
            "es": "Norteamérica",
            "fr": "Amérique du Nord",
            "ja": "北アメリカ",
            "pt-BR": "América do Norte",
            "ru": "Северная Америка",
            "zh-CN": "北美洲"
          }
        },
        "country": {
          "geoname_id": 6252001,
          "iso_code": "US",
          "names": {
            "de": "Vereinigte Staaten",
            "en": "United States",
            "es": "Estados Unidos",
            "fr": "États Unis",
            "ja": "アメリカ",
            "pt-BR": "EUA",
            "ru": "США",
            "zh-CN": "美国"
          }
        },
        "location": {
          "accuracy_radius": 1000,
          "latitude": 37.751,
          "longitude": -97.822,
          "time_zone": "America/Chicago"
        },
        "registered_country": {
          "geoname_id": 6252001,
          "iso_code": "US",
          "names": {
            "de": "Vereinigte Staaten",
            "en": "United States",
            "es": "Estados Unidos",
            "fr": "États Unis",
            "ja": "アメリカ",
            "pt-BR": "EUA",
            "ru": "США",
            "zh-CN": "美国"
          }
        }
      }
    },
    {
      "hostname": "upload.wikimedia.org",
      "ip": "198.35.26.112",
      "geoip": {
        "continent": {
          "code": "NA",
          "geoname_id": 6255149,
          "names": {
            "de": "Nordamerika",
            "en": "North America",
            "es": "Norteamérica",
            "fr": "Amérique du Nord",
            "ja": "北アメリカ",
            "pt-BR": "América do Norte",
            "ru": "Северная Америка",
            "zh-CN": "北美洲"
          }
        },
        "country": {
          "geoname_id": 6252001,
          "iso_code": "US",
          "names": {
            "de": "Vereinigte Staaten",
            "en": "United States",
            "es": "Estados Unidos",
            "fr": "États Unis",
            "ja": "アメリカ",
            "pt-BR": "EUA",
            "ru": "США",
            "zh-CN": "美国"
          }
        },
        "location": {
          "accuracy_radius": 1000,
          "latitude": 37.751,
          "longitude": -97.822,
          "time_zone": "America/Chicago"
        },
        "registered_country": {
          "geoname_id": 6252001,
          "iso_code": "US",
          "names": {
            "de": "Vereinigte Staaten",
            "en": "United States",
            "es": "Estados Unidos",
            "fr": "États Unis",
            "ja": "アメリカ",
            "pt-BR": "EUA",
            "ru": "США",
            "zh-CN": "美国"
          }
        }
      }
    }
  ]
}
